CHANGELOG.md
LICENSE
MANIFEST.in
README.md
setup.cfg
setup.py
ocean_provider/__init__.py
ocean_provider/config.py
ocean_provider/constants.py
ocean_provider/exceptions.py
ocean_provider/log.py
ocean_provider/myapp.py
ocean_provider/routes.py
ocean_provider/run.py
ocean_provider/user_nonce.py
ocean_provider/util.py
ocean_provider/utils/__init__.py
ocean_provider/utils/accounts.py
ocean_provider/utils/basics.py
ocean_provider/utils/data_token.py
ocean_provider/utils/encryption.py
ocean_provider/utils/web3.py
ocean_provider_plus.egg-info/PKG-INFO
ocean_provider_plus.egg-info/SOURCES.txt
ocean_provider_plus.egg-info/dependency_links.txt
ocean_provider_plus.egg-info/not-zip-safe
ocean_provider_plus.egg-info/requires.txt
ocean_provider_plus.egg-info/top_level.txt
tests/__init__.py
tests/conftest.py
tests/test_compute.py
tests/test_download.py
tests/test_helpers.py
tests/ddo/ddo_sa_sample.json
tests/ddo/ddo_sample_algorithm.json
tests/ddo/ddo_with_compute_service.json
tests/resources/consumer_key_file.json
tests/resources/provider_key_file.json